{
  "service_address": "0.0.0.0:7676",
  "secret_token": "some_secret_token",

  "logger": {
    "level": "dev",
    "dir_path": "optional_value__path_to_log_dir"
  },

  "metastorage": {
    "postgres": {
      "host": "",
      "port": "",
      "user": "",
      "password": "",
      "dbname": ""
    }
  },

  "s3": {
    "url": "https://storage.yandexcloud.net",
    "partition_id": "yc",
    "signing_region": "ru-central1",

    "credentials": {
      "access_key_id": "some_access_key",
      "secret_access_key": "some_secret_key"
    }
  }
}